openmdao/.pylintrc
openmdao/__init__.py
openmdao/__main__.py
openmdao/api.py
openmdao/func_api.py
openmdao/parallel_api.py
openmdao/approximation_schemes/__init__.py
openmdao/approximation_schemes/approximation_scheme.py
openmdao/approximation_schemes/complex_step.py
openmdao/approximation_schemes/finite_difference.py
openmdao/code_review/__init__.py
openmdao/code_review/test_common_problems.py
openmdao/code_review/test_lint_attributes.py
openmdao/components/__init__.py
openmdao/components/add_subtract_comp.py
openmdao/components/balance_comp.py
openmdao/components/cross_product_comp.py
openmdao/components/dot_product_comp.py
openmdao/components/eq_constraint_comp.py
openmdao/components/exec_comp.py
openmdao/components/explicit_func_comp.py
openmdao/components/external_code_comp.py
openmdao/components/func_comp_common.py
openmdao/components/implicit_func_comp.py
openmdao/components/input_resids_comp.py
openmdao/components/jax_explicit_comp.py
openmdao/components/jax_implicit_comp.py
openmdao/components/ks_comp.py
openmdao/components/linear_system_comp.py
openmdao/components/matrix_vector_product_comp.py
openmdao/components/meta_model_semi_structured_comp.py
openmdao/components/meta_model_structured_comp.py
openmdao/components/meta_model_unstructured_comp.py
openmdao/components/multifi_meta_model_unstructured_comp.py
openmdao/components/mux_comp.py
openmdao/components/spline_comp.py
openmdao/components/submodel_comp.py
openmdao/components/vector_magnitude_comp.py
openmdao/components/interp_util/__init__.py
openmdao/components/interp_util/interp.py
openmdao/components/interp_util/interp_akima.py
openmdao/components/interp_util/interp_algorithm.py
openmdao/components/interp_util/interp_bsplines.py
openmdao/components/interp_util/interp_cubic.py
openmdao/components/interp_util/interp_lagrange2.py
openmdao/components/interp_util/interp_lagrange3.py
openmdao/components/interp_util/interp_scipy.py
openmdao/components/interp_util/interp_semi.py
openmdao-3.42.0.dist-info/METADATA
openmdao-3.42.0.dist-info/WHEEL
openmdao-3.42.0.dist-info/entry_points.txt
openmdao-3.42.0.dist-info/licenses/LICENSE.txt
openmdao-3.42.0.dist-info/RECORD
