Metadata-Version: 2.4
Name: openmdao
Version: 3.42.0
Summary: OpenMDAO framework infrastructure
Project-URL: Homepage, http://openmdao.org
Author-email: OpenMDAO Team <openmdao@openmdao.org>
License-Expression: Apache-2.0
License-File: LICENSE.txt
Keywords: analysis,multi-disciplinary,multidisciplinary,optimization
Classifier: Development Status :: 5 - Production/Stable
Classifier: Intended Audience :: Science/Research
Classifier: License :: OSI Approved :: Apache Software License
Classifier: Natural Language :: English
Classifier: Operating System :: MacOS :: MacOS X
Classifier: Operating System :: Microsoft :: Windows
Classifier: Operating System :: POSIX :: Linux
Classifier: Programming Language :: Python
Classifier: Programming Language :: Python :: 3
Classifier: Programming Language :: Python :: Implementation :: CPython
Classifier: Topic :: Scientific/Engineering
Requires-Python: >=3.10
Requires-Dist: networkx>=3.3
Requires-Dist: numpy!=2.4.0,>=2.0
Requires-Dist: packaging
Requires-Dist: requests
Requires-Dist: scipy>=1.13
Provides-Extra: all
Requires-Dist: aiounittest; extra == 'all'
Requires-Dist: bokeh>=3.4.0; extra == 'all'
Requires-Dist: colorama; extra == 'all'
Requires-Dist: idna>=3.7; extra == 'all'
Requires-Dist: ipympl; extra == 'all'
Requires-Dist: ipyparallel; extra == 'all'
Requires-Dist: jax>=0.4.0; extra == 'all'
Requires-Dist: jaxlib>=0.4.0; extra == 'all'
Requires-Dist: jinja2>=3.1.4; extra == 'all'
Requires-Dist: jupyter-book<2,>=1.0.3; extra == 'all'
Requires-Dist: matplotlib; extra == 'all'
Requires-Dist: notebook; extra == 'all'
Requires-Dist: num2words; extra == 'all'
Requires-Dist: numpydoc>=1.1; extra == 'all'
Requires-Dist: panel; extra == 'all'
Requires-Dist: parameterized; extra == 'all'
Requires-Dist: playwright>=1.20; extra == 'all'
Requires-Dist: pre-commit; extra == 'all'
Requires-Dist: pycodestyle>=2.4.0; extra == 'all'
Requires-Dist: pydocstyle>=2.0.0; extra == 'all'
Requires-Dist: pydoe3; extra == 'all'
Requires-Dist: rich; extra == 'all'
Requires-Dist: sphinx-sitemap; extra == 'all'
Requires-Dist: testflo>=1.3.6; extra == 'all'
Requires-Dist: tqdm>=4.66.3; extra == 'all'
Requires-Dist: websockets>8; extra == 'all'
Provides-Extra: docs
Requires-Dist: idna>=3.7; extra == 'docs'
Requires-Dist: ipyparallel; extra == 'docs'
Requires-Dist: jinja2>=3.1.4; extra == 'docs'
Requires-Dist: jupyter-book<2,>=1.0.3; extra == 'docs'
Requires-Dist: matplotlib; extra == 'docs'
Requires-Dist: numpydoc>=1.1; extra == 'docs'
Requires-Dist: sphinx-sitemap; extra == 'docs'
Requires-Dist: tqdm>=4.66.3; extra == 'docs'
Provides-Extra: doe
Requires-Dist: pydoe3; extra == 'doe'
Provides-Extra: jax
Requires-Dist: jax>=0.4.0; extra == 'jax'
Requires-Dist: jaxlib>=0.4.0; extra == 'jax'
Provides-Extra: notebooks
Requires-Dist: idna>=3.7; extra == 'notebooks'
Requires-Dist: ipympl; extra == 'notebooks'
Requires-Dist: notebook; extra == 'notebooks'
Provides-Extra: numba
Requires-Dist: numba; extra == 'numba'
Provides-Extra: test
Requires-Dist: aiounittest; extra == 'test'
Requires-Dist: num2words; extra == 'test'
Requires-Dist: numpydoc>=1.1; extra == 'test'
Requires-Dist: parameterized; extra == 'test'
Requires-Dist: playwright>=1.20; extra == 'test'
Requires-Dist: pre-commit; extra == 'test'
Requires-Dist: pycodestyle>=2.4.0; extra == 'test'
Requires-Dist: pydocstyle>=2.0.0; extra == 'test'
Requires-Dist: testflo>=1.3.6; extra == 'test'
Requires-Dist: websockets>8; extra == 'test'
Provides-Extra: visualization
Requires-Dist: bokeh>=3.4.0; extra == 'visualization'
Requires-Dist: colorama; extra == 'visualization'
Requires-Dist: matplotlib; extra == 'visualization'
Requires-Dist: panel; extra == 'visualization'
Requires-Dist: rich; extra == 'visualization'
